ccl_lexer/__init__.py
ccl_lexer/ccl_definition.py
ccl_lexer/definitions.py
pygments_ccl_lexer-0.8.39.dist-info/DESCRIPTION.rst
pygments_ccl_lexer-0.8.39.dist-info/METADATA
pygments_ccl_lexer-0.8.39.dist-info/RECORD
pygments_ccl_lexer-0.8.39.dist-info/WHEEL
pygments_ccl_lexer-0.8.39.dist-info/entry_points.txt
pygments_ccl_lexer-0.8.39.dist-info/metadata.json
pygments_ccl_lexer-0.8.39.dist-info/top_level.txt
