Metadata-Version: 2.0
Name: pygments-ccl-lexer
Version: 0.8.39
Summary: Pygments lexer for CCL
Home-page: https://github.com/daftscience/pygments-ccl-lexer
Author: Thomas J. Perry
Author-email: admin@daftscience.com
License: GPL
Keywords: pygments ccl lexer
Platform: UNKNOWN
Requires-Dist: pygments (>=1.4)
